hackerman/__init__.py
hackerman/hashing.py
hackerman/utils.py
hackerman/_hashing/__init__.py
hackerman/_hashing/natzil.py
hackerman/crypto/__init__.py
hackerman/crypto/btc.py
hackerman/crypto/fernet.py
hackerman/crypto/hmc.py
hackerman/crypto/onion.py
hackerman/crypto/rsa.py
hackerman/crypto/wrapper.py
hackerman/crypto/xor.py
hackerman/handlers/__init__.py
hackerman/handlers/bind_base.py
hackerman/handlers/bind_tcp.py
hackerman/handlers/reverse_base.py
hackerman/handlers/reverse_dns.py
hackerman/handlers/reverse_http.py
hackerman/handlers/reverse_tcp.py
hackerman/payloads/__init__.py
hackerman/payloads/bind/__init__.py
hackerman/payloads/bind/_http.py
hackerman/payloads/bind/base.py
hackerman/payloads/bind/tcp.py
hackerman/payloads/reverse/__init__.py
hackerman/payloads/reverse/_http.py
hackerman/payloads/reverse/base.py
hackerman/payloads/reverse/dns.py
hackerman/payloads/reverse/tcp.py
hackerman/rat/__init__.py
hackerman/rat/gui/__init__.py
hackerman/rat/gui/keyboard.py
hackerman/rat/gui/screenshot.py
hackerman/scanners/__init__.py
hackerman/scanners/_http.py
hackerman/scanners/tcp.py
hackerman/stagers/__init__.py
hackerman/stagers/_http.py
hackerman/stagers/tcp.py
hackerman/stagers/examples/__init__.py
hackerman/stagers/examples/_http.py
hackerman/stagers/examples/tcp.py
hackerman/transport/__init__.py
hackerman/transport/arp.py
hackerman/transport/dns.py
hackerman/transport/dot11.py
hackerman/transport/fileio.py
hackerman/transport/smtp.py
hackerman/transport/tcp.py
hackerman/transport/covert/__init__.py
hackerman/transport/covert/dns.py
hackerman/transport/covert/dot11.py
hackerman/transport/covert/jsc.py
hackerman/ui/__init__.py
hackerman/ui/betterexec.py
hackerman/ui/daemon.py
hackerman/ui/output.py
hackerman/ui/pipe.py
hackerman/ui/shell.py
hackerman-0.99.2.dist-info/LICENSE
hackerman-0.99.2.dist-info/METADATA
hackerman-0.99.2.dist-info/WHEEL
hackerman-0.99.2.dist-info/top_level.txt
hackerman-0.99.2.dist-info/RECORD
