Metadata-Version: 2.1
Name: hackerman
Version: 0.99.2
Summary: A python library for penetration testing, security, development, and fun.
Home-page: https://github.com/AgeOfMarcus/hackerman
Author: Marcus Weinberger
Author-email: marcus@marcusweinberger.com
License: GPL
Platform: UNKNOWN
License-File: LICENSE
Requires-Dist: cryptography
Requires-Dist: flask
Requires-Dist: flask-cors
Requires-Dist: requests
Requires-Dist: scapy
Requires-Dist: pyscreenshot
Requires-Dist: pynput
Requires-Dist: qrcode
Requires-Dist: bitcoin
Requires-Dist: sympy
